[
  {
    "DocumentId": "https://www.themoviedb.org/movie/268",
    "title": "Batman",
    "0Invalid-Field": "Have you ever danced with the devil in the pale moonlight?",
    "Actors": ["Jack Nicholson", "Michael Keaton", "Kim Basinger"],
    "poster-A": "//image.tmdb.org/t/p/w185_and_h278_bestv2/kBf3g9crrADGMc2AMAMlLBgSm2h.jpg"
  },
  {
    "DocumentId": "https://www.themoviedb.org/movie/999",
    "title": "Batman 999",
    "data": "Batman (999) \n Based on the Character created by Bob Kane. \n EXT. CITYSCAPE - NIGHT \n Gotham City.  The City of Tomorrow:  stark angles, creeping shadows, dense, crowded, as if hell had erupted through the sidewalks.  A dangling fat moon shines overhead. \n At the opposite corner of the roof, some fifteen yards away... at the end of a line, a STRANGE BLACK SILHOUETTE is dropping slowly, implacably, into frame...",
    "789K^&*JFG*H9j*&(H": "Have you ever danced with the devil in the pale moonlight?",
    "Actors": ["Jack Nicholson", "Michael Keaton", "Kim Basinger"],
    "poster-A": "//image.tmdb.org/t/p/w185_and_h278_bestv2/kBf3g9crrADGMc2AMAMlLBgSm2h.jpg"
  }
]
